{
  "openapi": "3.0.1",
  "info": {
    "title": "AuthAPI",
    "version": "1.0"
  },
  "paths": {
    "/api/Auth/register": {
      "post": {
        "tags": [
          "Auth"
        ],
        "requestBody": {
          "content": {
            "application/json": {
              "schema": {
                "$ref": "#/components/schemas/RegisterModel"
              }
            },
            "text/json": {
              "schema": {
                "$ref": "#/components/schemas/RegisterModel"
              }
            },
            "application/*+json": {
              "schema": {
                "$ref": "#/components/schemas/RegisterModel"
              }
            }
          }
        },
        "responses": {
          "200": {
            "description": "OK"
          }
        }
      }
    },
    "/api/Auth/login": {
      "post": {
        "tags": [
          "Auth"
        ],
        "requestBody": {
          "content": {
            "application/json": {
              "schema": {
                "$ref": "#/components/schemas/LoginModel"
              }
            },
            "text/json": {
              "schema": {
                "$ref": "#/components/schemas/LoginModel"
              }
            },
            "application/*+json": {
              "schema": {
                "$ref": "#/components/schemas/LoginModel"
              }
            }
          }
        },
        "responses": {
          "200": {
            "description": "OK"
          }
        }
      }
    },
    "/api/Auth/logout": {
      "post": {
        "tags": [
          "Auth"
        ],
        "responses": {
          "200": {
            "description": "OK"
          }
        }
      }
    },
    "/api/Comments": {
      "post": {
        "tags": [
          "Comments"
        ],
        "requestBody": {
          "content": {
            "application/json": {
              "schema": {
                "$ref": "#/components/schemas/CommentModel"
              }
            },
            "text/json": {
              "schema": {
                "$ref": "#/components/schemas/CommentModel"
              }
            },
            "application/*+json": {
              "schema": {
                "$ref": "#/components/schemas/CommentModel"
              }
            }
          }
        },
        "responses": {
          "200": {
            "description": "OK"
          }
        }
      }
    },
    "/api/Rating": {
      "post": {
        "tags": [
          "Rating"
        ],
        "requestBody": {
          "content": {
            "application/json": {
              "schema": {
                "$ref": "#/components/schemas/RatingModel"
              }
            },
            "text/json": {
              "schema": {
                "$ref": "#/components/schemas/RatingModel"
              }
            },
            "application/*+json": {
              "schema": {
                "$ref": "#/components/schemas/RatingModel"
              }
            }
          }
        },
        "responses": {
          "200": {
            "description": "OK"
          }
        }
      }
    },
    "/api/Recipe": {
      "get": {
        "tags": [
          "Recipe"
        ],
        "parameters": [
          {
            "name": "Title",
            "in": "query",
            "schema": {
              "type": "string"
            }
          },
          {
            "name": "Category",
            "in": "query",
            "schema": {
              "type": "string"
            }
          },
          {
            "name": "Ingredient",
            "in": "query",
            "schema": {
              "type": "string"
            }
          },
          {
            "name": "PageNumber",
            "in": "query",
            "schema": {
              "type": "integer",
              "format": "int32"
            }
          },
          {
            "name": "PageSize",
            "in": "query",
            "schema": {
              "type": "integer",
              "format": "int32"
            }
          }
        ],
        "responses": {
          "200": {
            "description": "OK",
            "content": {
              "text/plain": {
                "schema": {
                  "$ref": "#/components/schemas/RecipePagedResult"
                }
              },
              "application/json": {
                "schema": {
                  "$ref": "#/components/schemas/RecipePagedResult"
                }
              },
              "text/json": {
                "schema": {
                  "$ref": "#/components/schemas/RecipePagedResult"
                }
              }
            }
          }
        }
      },
      "post": {
        "tags": [
          "Recipe"
        ],
        "requestBody": {
          "content": {
            "application/json": {
              "schema": {
                "$ref": "#/components/schemas/RecipeModel"
              }
            },
            "text/json": {
              "schema": {
                "$ref": "#/components/schemas/RecipeModel"
              }
            },
            "application/*+json": {
              "schema": {
                "$ref": "#/components/schemas/RecipeModel"
              }
            }
          }
        },
        "responses": {
          "200": {
            "description": "OK",
            "content": {
              "text/plain": {
                "schema": {
                  "$ref": "#/components/schemas/Recipe"
                }
              },
              "application/json": {
                "schema": {
                  "$ref": "#/components/schemas/Recipe"
                }
              },
              "text/json": {
                "schema": {
                  "$ref": "#/components/schemas/Recipe"
                }
              }
            }
          }
        }
      }
    },
    "/api/Recipe/{id}": {
      "get": {
        "tags": [
          "Recipe"
        ],
        "parameters": [
          {
            "name": "id",
            "in": "path",
            "required": true,
            "schema": {
              "type": "integer",
              "format": "int32"
            }
          }
        ],
        "responses": {
          "200": {
            "description": "OK",
            "content": {
              "text/plain": {
                "schema": {
                  "$ref": "#/components/schemas/Recipe"
                }
              },
              "application/json": {
                "schema": {
                  "$ref": "#/components/schemas/Recipe"
                }
              },
              "text/json": {
                "schema": {
                  "$ref": "#/components/schemas/Recipe"
                }
              }
            }
          }
        }
      },
      "put": {
        "tags": [
          "Recipe"
        ],
        "parameters": [
          {
            "name": "id",
            "in": "path",
            "required": true,
            "schema": {
              "type": "integer",
              "format": "int32"
            }
          }
        ],
        "requestBody": {
          "content": {
            "application/json": {
              "schema": {
                "$ref": "#/components/schemas/RecipeModel"
              }
            },
            "text/json": {
              "schema": {
                "$ref": "#/components/schemas/RecipeModel"
              }
            },
            "application/*+json": {
              "schema": {
                "$ref": "#/components/schemas/RecipeModel"
              }
            }
          }
        },
        "responses": {
          "200": {
            "description": "OK"
          }
        }
      },
      "delete": {
        "tags": [
          "Recipe"
        ],
        "parameters": [
          {
            "name": "id",
            "in": "path",
            "required": true,
            "schema": {
              "type": "integer",
              "format": "int32"
            }
          }
        ],
        "responses": {
          "200": {
            "description": "OK"
          }
        }
      }
    },
    "/api/User": {
      "get": {
        "tags": [
          "User"
        ],
        "responses": {
          "200": {
            "description": "OK"
          }
        }
      }
    },
    "/api/User/{id}": {
      "get": {
        "tags": [
          "User"
        ],
        "parameters": [
          {
            "name": "id",
            "in": "path",
            "required": true,
            "schema": {
              "type": "string"
            }
          }
        ],
        "responses": {
          "200": {
            "description": "OK"
          }
        }
      }
    },
    "/WeatherForecast": {
      "get": {
        "tags": [
          "WeatherForecast"
        ],
        "operationId": "GetWeatherForecast",
        "responses": {
          "200": {
            "description": "OK",
            "content": {
              "text/plain": {
                "schema": {
                  "type": "array",
                  "items": {
                    "$ref": "#/components/schemas/WeatherForecast"
                  }
                }
              },
              "application/json": {
                "schema": {
                  "type": "array",
                  "items": {
                    "$ref": "#/components/schemas/WeatherForecast"
                  }
                }
              },
              "text/json": {
                "schema": {
                  "type": "array",
                  "items": {
                    "$ref": "#/components/schemas/WeatherForecast"
                  }
                }
              }
            }
          }
        }
      }
    }
  },
  "components": {
    "schemas": {
      "ApplicationUser": {
        "type": "object",
        "properties": {
          "id": {
            "type": "string",
            "nullable": true
          },
          "userName": {
            "type": "string",
            "nullable": true
          },
          "normalizedUserName": {
            "type": "string",
            "nullable": true
          },
          "email": {
            "type": "string",
            "nullable": true
          },
          "normalizedEmail": {
            "type": "string",
            "nullable": true
          },
          "emailConfirmed": {
            "type": "boolean"
          },
          "passwordHash": {
            "type": "string",
            "nullable": true
          },
          "securityStamp": {
            "type": "string",
            "nullable": true
          },
          "concurrencyStamp": {
            "type": "string",
            "nullable": true
          },
          "phoneNumber": {
            "type": "string",
            "nullable": true
          },
          "phoneNumberConfirmed": {
            "type": "boolean"
          },
          "twoFactorEnabled": {
            "type": "boolean"
          },
          "lockoutEnd": {
            "type": "string",
            "format": "date-time",
            "nullable": true
          },
          "lockoutEnabled": {
            "type": "boolean"
          },
          "accessFailedCount": {
            "type": "integer",
            "format": "int32"
          },
          "name": {
            "type": "string",
            "nullable": true
          }
        },
        "additionalProperties": false
      },
      "Comment": {
        "type": "object",
        "properties": {
          "id": {
            "type": "integer",
            "format": "int32"
          },
          "content": {
            "type": "string",
            "nullable": true
          },
          "createdAt": {
            "type": "string",
            "format": "date-time"
          },
          "userId": {
            "type": "string",
            "nullable": true
          },
          "user": {
            "$ref": "#/components/schemas/ApplicationUser"
          },
          "recipeId": {
            "type": "integer",
            "format": "int32"
          },
          "recipe": {
            "$ref": "#/components/schemas/Recipe"
          }
        },
        "additionalProperties": false
      },
      "CommentModel": {
        "type": "object",
        "properties": {
          "recipeId": {
            "type": "integer",
            "format": "int32"
          },
          "content": {
            "type": "string",
            "nullable": true
          }
        },
        "additionalProperties": false
      },
      "Ingredient": {
        "type": "object",
        "properties": {
          "id": {
            "type": "integer",
            "format": "int32"
          },
          "name": {
            "type": "string",
            "nullable": true
          },
          "recipeId": {
            "type": "integer",
            "format": "int32"
          },
          "recipe": {
            "$ref": "#/components/schemas/Recipe"
          }
        },
        "additionalProperties": false
      },
      "Instruction": {
        "required": [
          "step"
        ],
        "type": "object",
        "properties": {
          "id": {
            "type": "integer",
            "format": "int32"
          },
          "step": {
            "minLength": 1,
            "type": "string"
          },
          "order": {
            "type": "integer",
            "format": "int32"
          },
          "recipeId": {
            "type": "integer",
            "format": "int32"
          },
          "recipe": {
            "$ref": "#/components/schemas/Recipe"
          }
        },
        "additionalProperties": false
      },
      "LoginModel": {
        "required": [
          "email",
          "password"
        ],
        "type": "object",
        "properties": {
          "email": {
            "minLength": 1,
            "type": "string",
            "format": "email"
          },
          "password": {
            "minLength": 1,
            "type": "string"
          }
        },
        "additionalProperties": false
      },
      "Rating": {
        "type": "object",
        "properties": {
          "id": {
            "type": "integer",
            "format": "int32"
          },
          "value": {
            "type": "integer",
            "format": "int32"
          },
          "userId": {
            "type": "string",
            "nullable": true
          },
          "user": {
            "$ref": "#/components/schemas/ApplicationUser"
          },
          "recipeId": {
            "type": "integer",
            "format": "int32"
          },
          "recipe": {
            "$ref": "#/components/schemas/Recipe"
          }
        },
        "additionalProperties": false
      },
      "RatingModel": {
        "type": "object",
        "properties": {
          "recipeId": {
            "type": "integer",
            "format": "int32"
          },
          "value": {
            "type": "integer",
            "format": "int32"
          }
        },
        "additionalProperties": false
      },
      "Recipe": {
        "type": "object",
        "properties": {
          "id": {
            "type": "integer",
            "format": "int32"
          },
          "title": {
            "type": "string",
            "nullable": true
          },
          "description": {
            "type": "string",
            "nullable": true
          },
          "category": {
            "type": "string",
            "nullable": true
          },
          "imageUrl": {
            "type": "string",
            "nullable": true
          },
          "userId": {
            "type": "string",
            "nullable": true
          },
          "user": {
            "$ref": "#/components/schemas/ApplicationUser"
          },
          "instructions": {
            "type": "array",
            "items": {
              "$ref": "#/components/schemas/Instruction"
            },
            "nullable": true
          },
          "ingredients": {
            "type": "array",
            "items": {
              "$ref": "#/components/schemas/Ingredient"
            },
            "nullable": true
          },
          "comments": {
            "type": "array",
            "items": {
              "$ref": "#/components/schemas/Comment"
            },
            "nullable": true
          },
          "ratings": {
            "type": "array",
            "items": {
              "$ref": "#/components/schemas/Rating"
            },
            "nullable": true
          }
        },
        "additionalProperties": false
      },
      "RecipeModel": {
        "type": "object",
        "properties": {
          "title": {
            "type": "string",
            "nullable": true
          },
          "description": {
            "type": "string",
            "nullable": true
          },
          "category": {
            "type": "string",
            "nullable": true
          },
          "imageUrl": {
            "type": "string",
            "nullable": true
          },
          "ingredients": {
            "type": "array",
            "items": {
              "type": "string"
            },
            "nullable": true
          },
          "instructions": {
            "type": "array",
            "items": {
              "type": "string"
            },
            "nullable": true
          }
        },
        "additionalProperties": false
      },
      "RecipePagedResult": {
        "type": "object",
        "properties": {
          "items": {
            "type": "array",
            "items": {
              "$ref": "#/components/schemas/Recipe"
            },
            "nullable": true
          },
          "totalCount": {
            "type": "integer",
            "format": "int32"
          },
          "pageNumber": {
            "type": "integer",
            "format": "int32"
          },
          "pageSize": {
            "type": "integer",
            "format": "int32"
          }
        },
        "additionalProperties": false
      },
      "RegisterModel": {
        "required": [
          "email",
          "name",
          "password",
          "username"
        ],
        "type": "object",
        "properties": {
          "name": {
            "minLength": 1,
            "type": "string"
          },
          "username": {
            "minLength": 1,
            "type": "string"
          },
          "email": {
            "minLength": 1,
            "type": "string",
            "format": "email"
          },
          "password": {
            "minLength": 1,
            "type": "string"
          }
        },
        "additionalProperties": false
      },
      "WeatherForecast": {
        "type": "object",
        "properties": {
          "date": {
            "type": "string",
            "format": "date"
          },
          "temperatureC": {
            "type": "integer",
            "format": "int32"
          },
          "temperatureF": {
            "type": "integer",
            "format": "int32",
            "readOnly": true
          },
          "summary": {
            "type": "string",
            "nullable": true
          }
        },
        "additionalProperties": false
      }
    }
  }
}